{
	"info": {
		"_postman_id": "2879a85d-a61f-4559-9e7a-771f0b923d60",
		"name": "Homework2ts",
		"schema": "https://schema.getpostman.com/json/collection/v2.1.0/collection.json",
		"_exporter_id": "42904584"
	},
	"item": [
		{
			"name": "localhost",
			"request": {
				"method": "GET",
				"header": [],
				"url": {
					"raw": "http://localhost:3000",
					"protocol": "http",
					"host": [
						"localhost"
					],
					"port": "3000"
				}
			},
			"response": []
		},
		{
			"name": "Get all",
			"request": {
				"method": "GET",
				"header": [],
				"url": {
					"raw": "http://localhost:3000/api/books",
					"protocol": "http",
					"host": [
						"localhost"
					],
					"port": "3000",
					"path": [
						"api",
						"books"
					]
				}
			},
			"response": []
		},
		{
			"name": "Get id",
			"request": {
				"method": "GET",
				"header": [],
				"url": {
					"raw": "http://localhost:3000/api/books/10",
					"protocol": "http",
					"host": [
						"localhost"
					],
					"port": "3000",
					"path": [
						"api",
						"books",
						"10"
					]
				}
			},
			"response": []
		},
		{
			"name": "create book",
			"request": {
				"method": "POST",
				"header": [],
				"body": {
					"mode": "raw",
					"raw": "{\r\n  \"id\": 11,\r\n  \"title\": \"New Book\",\r\n  \"author\": \"New Author\",\r\n  \"price\": 25\r\n}",
					"options": {
						"raw": {
							"language": "json"
						}
					}
				},
				"url": {
					"raw": "http://localhost:3000/api/books",
					"protocol": "http",
					"host": [
						"localhost"
					],
					"port": "3000",
					"path": [
						"api",
						"books"
					]
				}
			},
			"response": []
		},
		{
			"name": "update book",
			"request": {
				"method": "PUT",
				"header": [],
				"body": {
					"mode": "raw",
					"raw": "{\r\n  \"id\": 10,\r\n  \"title\": \"Angular\",\r\n  \"author\": \"Updated Author\",\r\n  \"price\": 30\r\n}",
					"options": {
						"raw": {
							"language": "json"
						}
					}
				},
				"url": {
					"raw": "http://localhost:3000/api/books/10",
					"protocol": "http",
					"host": [
						"localhost"
					],
					"port": "3000",
					"path": [
						"api",
						"books",
						"10"
					]
				}
			},
			"response": []
		},
		{
			"name": "delete book",
			"request": {
				"method": "DELETE",
				"header": [],
				"url": {
					"raw": "http://localhost:3000/api/books/11",
					"protocol": "http",
					"host": [
						"localhost"
					],
					"port": "3000",
					"path": [
						"api",
						"books",
						"11"
					]
				}
			},
			"response": []
		},
		{
			"name": "filter minPrice",
			"request": {
				"method": "GET",
				"header": [],
				"url": {
					"raw": "http://localhost:3000/api/books?minPrice=30",
					"protocol": "http",
					"host": [
						"localhost"
					],
					"port": "3000",
					"path": [
						"api",
						"books"
					],
					"query": [
						{
							"key": "minPrice",
							"value": "30"
						}
					]
				}
			},
			"response": []
		},
		{
			"name": "filter author",
			"request": {
				"method": "GET",
				"header": [],
				"url": {
					"raw": "http://localhost:3000/api/books?author=John%20Doe",
					"protocol": "http",
					"host": [
						"localhost"
					],
					"port": "3000",
					"path": [
						"api",
						"books"
					],
					"query": [
						{
							"key": "author",
							"value": "John%20Doe"
						}
					]
				}
			},
			"response": []
		}
	]
}